polars_ds-0.10.3.dist-info/METADATA
polars_ds-0.10.3.dist-info/WHEEL
polars_ds-0.10.3.dist-info/licenses/LICENSE.txt
polars_ds/_utils.py
polars_ds/partition/partition.py
polars_ds/partition/__init__.py
polars_ds/exprs/metrics.py
polars_ds/exprs/expr_linear.py
polars_ds/exprs/ts_features.py
polars_ds/exprs/num.py
polars_ds/exprs/expr_balltree.py
polars_ds/exprs/stats.py
polars_ds/exprs/string.py
polars_ds/exprs/expr_iter.py
polars_ds/exprs/expr_knn.py
polars_ds/exprs/__init__.py
polars_ds/typing.py
polars_ds/compat/_compat.py
polars_ds/compat/__init__.py
polars_ds/eda/plots.py
polars_ds/eda/diagnosis.py
polars_ds/eda/__init__.py
polars_ds/spatial.py
polars_ds/pipeline/transforms.py
polars_ds/pipeline/pipeline.py
polars_ds/pipeline/_step.py
polars_ds/pipeline/__init__.py
polars_ds/sample_and_split/sample_and_split.py
polars_ds/sample_and_split/__init__.py
polars_ds/linear_models.py
polars_ds/expander.py
polars_ds/config.py
polars_ds/__init__.py
polars_ds/_polars_ds.abi3.so
polars_ds-0.10.3.dist-info/RECORD
