Metadata-Version: 2.3
Name: polars_ds
Version: 0.10.3
Classifier: Development Status :: 4 - Beta
Classifier: Programming Language :: Rust
Classifier: Programming Language :: Python :: Implementation :: CPython
Classifier: Programming Language :: Python :: Implementation :: PyPy
Classifier: License :: OSI Approved :: MIT License
Requires-Dist: polars >=1.4.0, !=1.25, !=1.26, !=1.32.1, !=1.32.2
Requires-Dist: typing-extensions ; python_version <= '3.11'
Requires-Dist: great-tables >=0.9 ; extra == 'plot'
Requires-Dist: graphviz >=0.20 ; extra == 'plot'
Requires-Dist: altair >=5.4.0 ; extra == 'plot'
Requires-Dist: vegafusion[embed] ; extra == 'plot'
Requires-Dist: numpy >=1.16 ; extra == 'models'
Requires-Dist: numpy >=1.16 ; extra == 'compat'
Requires-Dist: great-tables >=0.9 ; extra == 'all'
Requires-Dist: graphviz >=0.20 ; extra == 'all'
Requires-Dist: numpy >=1.16 ; extra == 'all'
Requires-Dist: altair >=5.4.0 ; extra == 'all'
Requires-Dist: vegafusion[embed] ; extra == 'all'
Provides-Extra: plot
Provides-Extra: models
Provides-Extra: compat
Provides-Extra: all
License-File: LICENSE.txt
Keywords: polars-extension,scientific-computing,data-science
Author-email: Tianren Qin <tq9695@gmail.com>
Requires-Python: >=3.9
